llm_dataclass/__about__.py
llm_dataclass/__init__.py
llm_dataclass/py.typed
llm_dataclass/wrappers.py
llm_dataclass-1.1.5.dist-info/METADATA
llm_dataclass-1.1.5.dist-info/WHEEL
llm_dataclass-1.1.5.dist-info/licenses/LICENSE.txt
llm_dataclass-1.1.5.dist-info/RECORD
