Metadata-Version: 2.4
Name: llm-dataclass
Version: 1.1.5
Summary: A dataclass interface for llms
Project-URL: Issues, https://github.com/bytehexe/llm-dataclass/issues
Project-URL: Source, https://github.com/bytehexe/llm-dataclass
Author: Janna Hopp
License-Expression: MIT
License-File: LICENSE.txt
Classifier: Development Status :: 4 - Beta
Classifier: Programming Language :: Python
Classifier: Programming Language :: Python :: 3.8
Classifier: Programming Language :: Python :: 3.9
Classifier: Programming Language :: Python :: 3.10
Classifier: Programming Language :: Python :: 3.11
Classifier: Programming Language :: Python :: 3.12
Classifier: Programming Language :: Python :: Implementation :: CPython
Classifier: Programming Language :: Python :: Implementation :: PyPy
Requires-Python: >=3.8
Requires-Dist: lxml
Requires-Dist: xmltodict
